LICENSE
README.md
pyproject.toml
mongomotor/__init__.py
mongomotor/connection.py
mongomotor/context_managers.py
mongomotor/decorators.py
mongomotor/dereference.py
mongomotor/document.py
mongomotor/exceptions.py
mongomotor/fields.py
mongomotor/monkey.py
mongomotor/queryset.py
mongomotor/signals.py
mongomotor/utils.py
mongomotor.egg-info/PKG-INFO
mongomotor.egg-info/SOURCES.txt
mongomotor.egg-info/dependency_links.txt
mongomotor.egg-info/requires.txt
mongomotor.egg-info/top_level.txt