Metadata-Version: 2.4
Name: mongomotor
Version: 0.17.1
Summary: MongoMotor: An async document-object mapper for MongoDB
Author: Juca Crispim
Classifier: Development Status :: 3 - Alpha
Classifier: Intended Audience :: Developers
Classifier: License :: OSI Approved :: GNU General Public License (GPL)
Classifier: Natural Language :: English
Classifier: Operating System :: OS Independent
Classifier: Programming Language :: Python :: 3
Classifier: Topic :: Software Development :: Libraries :: Python Modules
Classifier: License :: OSI Approved :: GNU General Public License v3 (GPLv3)
License-File: LICENSE
Requires-Dist: mongoengine>=0.29.1
Requires-Dist: blinker>=1.5
Requires-Dist: pymongo>=4.9.0
Requires-Dist: asyncblink>=0.3.2
Dynamic: license-file
